efficient_likelihoods.so
mitre/__init__.py
mitre/command_line.py
mitre/efficient_likelihoods.c
mitre/efficient_likelihoods.pyx
mitre/key_comparison.py
mitre/lambda_quick_test.py
mitre/logit_rule_test.py
mitre/logit_rules.py
mitre/logit_test.py
mitre/main.py
mitre/mvnpdf_cholesky.py
mitre/posterior.py
mitre/prior_by_primitive.py
mitre/quick_test.cfg
mitre/rules.py
mitre/template.html
mitre/test.py
mitre/visualization.py
mitre/comparison_methods/__init__.py
mitre/comparison_methods/sklearn_wrappers.py
mitre/data_processing/__init__.py
mitre/data_processing/crossvalidation.py
mitre/data_processing/data_processing.py
mitre/data_processing/filtering.py
mitre/data_processing/sequencing.py
mitre/data_processing/synthetic_data.py
mitre/data_processing/transforms.py
mitre/example_data/CITATIONS.txt
mitre/example_data/example_settings.cfg
mitre/example_data/bokulich/NOTE
mitre/example_data/bokulich/abundance.csv
mitre/example_data/bokulich/dada2_placements.csv
mitre/example_data/bokulich/placement.jplace
mitre/example_data/bokulich/sample_metadata.csv
mitre/example_data/bokulich/sample_metadata_no_repeats.csv
mitre/example_data/bokulich/seq_info.csv
mitre/example_data/bokulich/sequence_key.fa
mitre/example_data/bokulich/subject_data.csv
mitre/example_data/bokulich/taxaTable.csv
mitre/example_data/david/abundance.csv
mitre/example_data/david/david_long.cfg.lsf
mitre/example_data/david/mothur_placements.csv
mitre/example_data/david/placements.jplace
mitre/example_data/david/sample_metadata.csv
mitre/example_data/david/seq_info.csv
mitre/example_data/david/sequence_key.fa
mitre/example_data/david/subject_data.csv
mitre/example_data/david/taxaTable.csv
mitre/example_data/digiulio/abundance.csv
mitre/example_data/digiulio/dada2_placements.csv
mitre/example_data/digiulio/placement.jplace
mitre/example_data/digiulio/sample_metadata.csv
mitre/example_data/digiulio/seq_info.csv
mitre/example_data/digiulio/sequence_key.fa
mitre-0.9b5.dist-info/DESCRIPTION.rst
mitre-0.9b5.dist-info/METADATA
mitre-0.9b5.dist-info/RECORD
mitre-0.9b5.dist-info/WHEEL
mitre-0.9b5.dist-info/entry_points.txt
mitre-0.9b5.dist-info/metadata.json
mitre-0.9b5.dist-info/top_level.txt
