Metadata-Version: 2.0
Name: mitre
Version: 0.9b5
Summary: Microbiome Interpretable Temporal Rule Engine
Home-page: http://github.com/gerberlab/mitre
Author: Eli Bogart
Author-email: ebogart@bwh.harvard.edu
License: GPLv3
Keywords: microbiome time-series bayesian-inference
Platform: UNKNOWN
Classifier: Development Status :: 4 - Beta
Classifier: Intended Audience :: Science/Research
Classifier: License :: OSI Approved :: GNU General Public License (GPL)
Classifier: Topic :: Scientific/Engineering :: Bio-Informatics
Requires-Dist: ete3
Requires-Dist: matplotlib
Requires-Dist: numpy
Requires-Dist: pandas (>0.20)
Requires-Dist: pypolyagamma
Requires-Dist: scikit-learn
Requires-Dist: scipy (>=0.17.1)
Requires-Dist: tqdm
